{
"type": "FeatureCollection",
"name": "DEPOMINYAK_PT_50K",
"crs": { "type": "name", "properties": { "name": "urn:ogc:def:crs:OGC:1.3:CRS84" } },
"features": [
{ "type": "Feature", "properties": { "NAMOBJ": "", "FCODE": " ", "REMARK": "Depo Bahan Bakar Minyak", "METADATA": null, "SRS_ID": " " }, "geometry": { "type": "Point", "coordinates": [ 104.741065238000033, -3.031613890999949, 0.0 ] } }
]
}
