{
"type": "FeatureCollection",
"name": "TERMINALBUS_PT_50K",
"crs": { "type": "name", "properties": { "name": "urn:ogc:def:crs:OGC:1.3:CRS84" } },
"features": [
{ "type": "Feature", "properties": { "NAMOBJ": "", "FCODE": " ", "REMARK": "Terminal Bus/Angkutan Kendaraan Lainnya", "METADATA": "RBI5000020221231PROVINSISUMATERASELATAN", "SRS_ID": " ", "JLBTRM": null, "JLDTRM": null, "KATTRM": null, "KODTRM": null, "KONKON": null, "MGTTRM": null, "PARTRM": null, "STATRM": null, "THBTRM": null, "THTTRM": null, "TIPTRM": null, "THNOPR": null }, "geometry": { "type": "Point", "coordinates": [ 104.652726648000055, -3.205741452999973, 0.0 ] } },
{ "type": "Feature", "properties": { "NAMOBJ": "", "FCODE": " ", "REMARK": "Terminal Bus/Angkutan Kendaraan Lainnya", "METADATA": "RBI5000020221231PROVINSISUMATERASELATAN", "SRS_ID": " ", "JLBTRM": null, "JLDTRM": null, "KATTRM": null, "KODTRM": null, "KONKON": null, "MGTTRM": null, "PARTRM": null, "STATRM": null, "THBTRM": null, "THTTRM": null, "TIPTRM": null, "THNOPR": null }, "geometry": { "type": "Point", "coordinates": [ 104.775164332000088, -3.025741000999972, 0.0 ] } },
{ "type": "Feature", "properties": { "NAMOBJ": "", "FCODE": " ", "REMARK": "Terminal Bus/Angkutan Kendaraan Lainnya", "METADATA": "RBI5000020221231PROVINSISUMATERASELATAN", "SRS_ID": " ", "JLBTRM": null, "JLDTRM": null, "KATTRM": null, "KODTRM": null, "KONKON": null, "MGTTRM": null, "PARTRM": null, "STATRM": null, "THBTRM": null, "THTTRM": null, "TIPTRM": null, "THNOPR": null }, "geometry": { "type": "Point", "coordinates": [ 104.681757865000066, -2.916575347999981, 0.0 ] } },
{ "type": "Feature", "properties": { "NAMOBJ": "", "FCODE": " ", "REMARK": "Terminal Bus/Angkutan Kendaraan Lainnya", "METADATA": "RBI5000020221231PROVINSISUMATERASELATAN", "SRS_ID": " ", "JLBTRM": null, "JLDTRM": null, "KATTRM": null, "KODTRM": null, "KONKON": null, "MGTTRM": null, "PARTRM": null, "STATRM": null, "THBTRM": null, "THTTRM": null, "TIPTRM": null, "THNOPR": null }, "geometry": { "type": "Point", "coordinates": [ 104.815197325000042, -2.997458575999929, 0.0 ] } }
]
}
